unipkg.py
src/__init__.py
src/check_other_pms.py
src/execute_command.py
src/get_commands.py
src/get_pms.py
src/logging.py
src/loop.py
src/settings.py
src/vars.py
unipkg-0.2.1.dist-info/LICENSE
unipkg-0.2.1.dist-info/METADATA
unipkg-0.2.1.dist-info/WHEEL
unipkg-0.2.1.dist-info/entry_points.txt
unipkg-0.2.1.dist-info/top_level.txt
unipkg-0.2.1.dist-info/RECORD
