Metadata-Version: 2.1
Name: unipkg
Version: 0.2.1
Summary: A unifying package manager command line tool
Home-page: https://github.com/SudoMakeMeASandwichDE/unipkg
Author: SudoMakeMeASandwichDE
Author-email: sudosandwich.contact@gmail.com
License: GPL-3.0-or-later
Classifier: License :: OSI Approved :: GNU General Public License v3 or later (GPLv3+)
Classifier: Operating System :: POSIX :: Linux
Classifier: Programming Language :: Python :: 3
Requires-Python: >=3.10
License-File: LICENSE
Requires-Dist: distro
